MANIFEST.in
README.md
setup.py
test/test_basic.py
test/test_monitor.py
test/test_ovs.py
test/test_parallel.py
test/test_twink.py
twink/__init__.py
twink/__main__.py
twink/base.py
twink/ovs.py
twink/sched_basic.py
twink/sched_gevent.py
twink.egg-info/PKG-INFO
twink.egg-info/SOURCES.txt
twink.egg-info/dependency_links.txt
twink.egg-info/top_level.txt
twink/ofp4/__init__.py
twink/ofp4/build.py
twink/ofp4/oxm.py
twink/ofp4/parse.py
twink/ofp5/__init__.py
twink/ofp5/__main__.py
twink/ofp5/build.py
twink/ofp5/oxm.py
twink/ofp5/parse.py