Metadata-Version: 2.1
Name: twink
Version: 0.3
Summary: Openflow library
Home-page: https://github.com/hkwi/twink/
Author: Hiroaki Kawai
Author-email: hiroaki.kawai@gmail.com
License: UNKNOWN
Platform: UNKNOWN
